common_butia/__init__.py
common_butia/common.py
common_butia/data.py
common_butia/metrics.py
common_butia/xlsx_to_csv.py
common_butia-0.2.0.data/data/common-butia-data/Alavancagem.xlsx
common_butia-0.2.0.data/data/common-butia-data/Ativos Total.xlsx
common_butia-0.2.0.data/data/common-butia-data/Margem Bruta.xlsx
common_butia-0.2.0.data/data/common-butia-data/Nefin.xlsx
common_butia-0.2.0.data/data/common-butia-data/ROA.xlsx
common_butia-0.2.0.data/data/common-butia-data/ROE.xlsx
common_butia-0.2.0.data/data/common-butia-data/ROIC.xlsx
common_butia-0.2.0.data/data/common-butia-data/Receita Líquida.xlsx
common_butia-0.2.0.data/data/common-butia-data/Volume.xlsx
common_butia-0.2.0.data/data/common-butia-data/cdi.xlsx
common_butia-0.2.0.data/data/common-butia-data/commodities-data.xlsx
common_butia-0.2.0.data/data/common-butia-data/eligible.xlsx
common_butia-0.2.0.data/data/common-butia-data/index-data.xlsx
common_butia-0.2.0.data/data/common-butia-data/juros-us.xlsx
common_butia-0.2.0.data/data/common-butia-data/market_beta.xlsx
common_butia-0.2.0.data/data/common-butia-data/market_cap.xlsx
common_butia-0.2.0.data/data/common-butia-data/metadata.txt
common_butia-0.2.0.data/data/common-butia-data/ohcl-ibov.xlsx
common_butia-0.2.0.data/data/common-butia-data/ohcl-smll.xlsx
common_butia-0.2.0.data/data/common-butia-data/ohcl-sp.xlsx
common_butia-0.2.0.data/data/common-butia-data/petr-vale-data.xlsx
common_butia-0.2.0.data/data/common-butia-data/precosAcoes.xlsx
common_butia-0.2.0.data/data/common-butia-data/price_book.xlsx
common_butia-0.2.0.data/data/common-butia-data/quant-ibov.xlsx
common_butia-0.2.0.data/data/common-butia-data/quant-spx.xlsx
common_butia-0.2.0.data/data/common-butia-data/retornos.xlsx
common_butia-0.2.0.data/data/common-butia-data/cambio/README.md
common_butia-0.2.0.data/data/common-butia-data/cambio/brcoindx.csv
common_butia-0.2.0.data/data/common-butia-data/cambio/cds.csv
common_butia-0.2.0.data/data/common-butia-data/cambio/contratos.csv
common_butia-0.2.0.dist-info/LICENSE
common_butia-0.2.0.dist-info/WHEEL
common_butia-0.2.0.dist-info/METADATA
common_butia-0.2.0.dist-info/RECORD
